sigma/backends/opensearch/__init__.py
sigma/backends/opensearch/opensearch.py
pysigma_backend_opensearch-1.0.4.dist-info/LICENSE
pysigma_backend_opensearch-1.0.4.dist-info/METADATA
pysigma_backend_opensearch-1.0.4.dist-info/WHEEL
pysigma_backend_opensearch-1.0.4.dist-info/RECORD
