Metadata-Version: 2.1
Name: pySigma-backend-opensearch
Version: 1.0.4
Summary: pySigma OpenSearch backend
Home-page: https://github.com/SigmaHQ/pySigma-backend-opensearch
License: LGPL-3.0-only
Author: Hendrik Baecker
Author-email: hendrik.baecker@dcso.de
Requires-Python: >=3.9,<4.0
Classifier: License :: OSI Approved :: GNU Lesser General Public License v3 (LGPLv3)
Classifier: Programming Language :: Python :: 3
Classifier: Programming Language :: Python :: 3.9
Classifier: Programming Language :: Python :: 3.10
Classifier: Programming Language :: Python :: 3.11
Classifier: Programming Language :: Python :: 3.12
Classifier: Programming Language :: Python :: 3.13
Requires-Dist: pysigma (>=0.10.2,<0.12.0)
Requires-Dist: pysigma-backend-elasticsearch (>=1.1.3,<2.0.0)
Project-URL: Repository, https://github.com/SigmaHQ/pySigma-backend-opensearch
